genomesearch/__init__.py
genomesearch/help.py
genomesearch/install.py
genomesearch/isolate.py
genomesearch/main.py
genomesearch/meta.py
genomesearch/prodigal.py
genomesearch/bin/diamond
genomesearch/bin/prodigal.linux
genomesearch/data/refbank_markers_one.tsv
genomesearch/data/refbank_markers_onezero.tsv
genomesearch/data/uhgg_markers_one.tsv
genomesearch/data/uhgg_markers_onezero.tsv
genomesearch-0.0.9.dev0.dist-info/METADATA
genomesearch-0.0.9.dev0.dist-info/WHEEL
genomesearch-0.0.9.dev0.dist-info/entry_points.txt
genomesearch-0.0.9.dev0.dist-info/top_level.txt
genomesearch-0.0.9.dev0.dist-info/RECORD
